nostredame/__init__.py
nostredame/background.py
nostredame/backup.py
nostredame/data.py
nostredame/file.py
nostredame/globals.py
nostredame/list.py
nostredame/prediction.py
nostredame/quality.py
nostredame/season.py
nostredame/string.py
nostredame/time.py
nostredame/trend.py
nostredame/values.py
nostredame-1.5.0.dist-info/LICENSE
nostredame-1.5.0.dist-info/METADATA
nostredame-1.5.0.dist-info/WHEEL
nostredame-1.5.0.dist-info/top_level.txt
nostredame-1.5.0.dist-info/RECORD
