Metadata-Version: 2.1
Name: nostredame
Version: 1.5.0
Summary: forecasts
Home-page: UNKNOWN
Author: Savino Piccolomo
Author-email: piccolomo@gmail.com
License: MIT
Platform: UNKNOWN
Requires-Python: >=3.1.0
License-File: LICENSE
Requires-Dist: matplotlib
Requires-Dist: numpy
Requires-Dist: statsmodels
